djangoessentials/__init__.py
djangoessentials/apps.py
djangoessentials/djangoessentials.py
djangoessentials/models.py
djangoessentials/repository.py
djangoessentials/service.py
djangoessentials/migrations/__init__.py
djangoessentials-0.2.4.dist-info/LICENSE
djangoessentials-0.2.4.dist-info/METADATA
djangoessentials-0.2.4.dist-info/WHEEL
djangoessentials-0.2.4.dist-info/top_level.txt
djangoessentials-0.2.4.dist-info/RECORD
