Metadata-Version: 2.2
Name: djangoessentials
Version: 0.2.4
Summary: A lightweight repository-service pattern library for Django applications.
Home-page: https://github.com/CoderMungan/DjangoEssentials
Author: CoderMungan
Author-email: codermungan@gmail.com
Classifier: Development Status :: 3 - Alpha
Classifier: Intended Audience :: Developers
Classifier: License :: OSI Approved :: MIT License
Classifier: Programming Language :: Python :: 3
Classifier: Programming Language :: Python :: 3.7
Classifier: Programming Language :: Python :: 3.8
Classifier: Programming Language :: Python :: 3.9
Classifier: Framework :: Django
Classifier: Framework :: Django :: 3.2
Classifier: Framework :: Django :: 4.0
Requires-Python: >=3.7
License-File: LICENSE
Requires-Dist: Django>=3.2
Requires-Dist: django-storages[boto3]>=1.11
Requires-Dist: djangorestframework>=3.12
Dynamic: author
Dynamic: author-email
Dynamic: classifier
Dynamic: description
Dynamic: description-content-type
Dynamic: home-page
Dynamic: requires-dist
Dynamic: requires-python
Dynamic: summary
